big_o_estimator/__init__.py
big_o_estimator/estimator.py
big_o_estimator/__pycache__/__init__.cpython-311.pyc
big_o_estimator/__pycache__/estimator.cpython-311.pyc
tests/__init__.py
tests/test_big_o_estimator.py
big_o_estimator-0.1.3.2.dist-info/LICENSE
big_o_estimator-0.1.3.2.dist-info/METADATA
big_o_estimator-0.1.3.2.dist-info/WHEEL
big_o_estimator-0.1.3.2.dist-info/top_level.txt
big_o_estimator-0.1.3.2.dist-info/RECORD
