Metadata-Version: 2.1
Name: big-o-estimator
Version: 0.1.3.2
Summary: A package to estimate Big-O complexity of Python functions.
Home-page: https://github.com/amukherjee1991/big_o_estimator_package
Author: Arghya 
Author-email: arghyazzz@gmail.com
License: MIT
Classifier: Programming Language :: Python :: 3
Classifier: License :: OSI Approved :: MIT License
Classifier: Operating System :: OS Independent
Requires-Python: >=3.10
License-File: LICENSE
